[{"name":"abstract fun d(tag: String, method: String, message: String)","description":"com.ivoafsilva.mobiweb.mobilesdk.common.LogContract.d","location":"-mobile-sdk/com.ivoafsilva.mobiweb.mobilesdk.common/-log-contract/d.html","searchKeys":["d","abstract fun d(tag: String, method: String, message: String)","com.ivoafsilva.mobiweb.mobilesdk.common.LogContract.d"]},{"name":"abstract fun e(tag: String, method: String, message: String)","description":"com.ivoafsilva.mobiweb.mobilesdk.common.LogContract.e","location":"-mobile-sdk/com.ivoafsilva.mobiweb.mobilesdk.common/-log-contract/e.html","searchKeys":["e","abstract fun e(tag: String, method: String, message: String)","com.ivoafsilva.mobiweb.mobilesdk.common.LogContract.e"]},{"name":"abstract fun i(tag: String, method: String, message: String)","description":"com.ivoafsilva.mobiweb.mobilesdk.common.LogContract.i","location":"-mobile-sdk/com.ivoafsilva.mobiweb.mobilesdk.common/-log-contract/i.html","searchKeys":["i","abstract fun i(tag: String, method: String, message: String)","com.ivoafsilva.mobiweb.mobilesdk.common.LogContract.i"]},{"name":"abstract fun v(tag: String, method: String, message: String)","description":"com.ivoafsilva.mobiweb.mobilesdk.common.LogContract.v","location":"-mobile-sdk/com.ivoafsilva.mobiweb.mobilesdk.common/-log-contract/v.html","searchKeys":["v","abstract fun v(tag: String, method: String, message: String)","com.ivoafsilva.mobiweb.mobilesdk.common.LogContract.v"]},{"name":"abstract fun w(tag: String, method: String, message: String)","description":"com.ivoafsilva.mobiweb.mobilesdk.common.LogContract.w","location":"-mobile-sdk/com.ivoafsilva.mobiweb.mobilesdk.common/-log-contract/w.html","searchKeys":["w","abstract fun w(tag: String, method: String, message: String)","com.ivoafsilva.mobiweb.mobilesdk.common.LogContract.w"]},{"name":"class MobileSdk : KoinComponent","description":"com.ivoafsilva.mobiweb.mobilesdk.MobileSdk","location":"-mobile-sdk/com.ivoafsilva.mobiweb.mobilesdk/-mobile-sdk/index.html","searchKeys":["MobileSdk","class MobileSdk : KoinComponent","com.ivoafsilva.mobiweb.mobilesdk.MobileSdk"]},{"name":"fun enableLogging(contract: LogContract)","description":"com.ivoafsilva.mobiweb.mobilesdk.MobileSdk.enableLogging","location":"-mobile-sdk/com.ivoafsilva.mobiweb.mobilesdk/-mobile-sdk/enable-logging.html","searchKeys":["enableLogging","fun enableLogging(contract: LogContract)","com.ivoafsilva.mobiweb.mobilesdk.MobileSdk.enableLogging"]},{"name":"interface LogContract","description":"com.ivoafsilva.mobiweb.mobilesdk.common.LogContract","location":"-mobile-sdk/com.ivoafsilva.mobiweb.mobilesdk.common/-log-contract/index.html","searchKeys":["LogContract","interface LogContract","com.ivoafsilva.mobiweb.mobilesdk.common.LogContract"]},{"name":"suspend fun logMessage(message: String): Boolean","description":"com.ivoafsilva.mobiweb.mobilesdk.MobileSdk.logMessage","location":"-mobile-sdk/com.ivoafsilva.mobiweb.mobilesdk/-mobile-sdk/log-message.html","searchKeys":["logMessage","suspend fun logMessage(message: String): Boolean","com.ivoafsilva.mobiweb.mobilesdk.MobileSdk.logMessage"]},{"name":"val mobileSdkModule: Module","description":"com.ivoafsilva.mobiweb.mobilesdk.di.mobileSdkModule","location":"-mobile-sdk/com.ivoafsilva.mobiweb.mobilesdk.di/mobile-sdk-module.html","searchKeys":["mobileSdkModule","val mobileSdkModule: Module","com.ivoafsilva.mobiweb.mobilesdk.di.mobileSdkModule"]}]
